odoo/addons/fleet_vehicle_service_calendar/README.rst
odoo/addons/fleet_vehicle_service_calendar/__init__.py
odoo/addons/fleet_vehicle_service_calendar/__manifest__.py
odoo/addons/fleet_vehicle_service_calendar/i18n/es.po
odoo/addons/fleet_vehicle_service_calendar/i18n/fleet_vehicle_service_calendar.pot
odoo/addons/fleet_vehicle_service_calendar/i18n/it.po
odoo/addons/fleet_vehicle_service_calendar/i18n/pt_BR.po
odoo/addons/fleet_vehicle_service_calendar/models/__init__.py
odoo/addons/fleet_vehicle_service_calendar/models/calendar_event.py
odoo/addons/fleet_vehicle_service_calendar/models/fleet_vehicle_log_services.py
odoo/addons/fleet_vehicle_service_calendar/readme/CONTRIBUTORS.rst
odoo/addons/fleet_vehicle_service_calendar/readme/DESCRIPTION.rst
odoo/addons/fleet_vehicle_service_calendar/static/description/icon.png
odoo/addons/fleet_vehicle_service_calendar/static/description/index.html
odoo/addons/fleet_vehicle_service_calendar/tests/__init__.py
odoo/addons/fleet_vehicle_service_calendar/tests/test_vehicle_service_calendar.py
odoo/addons/fleet_vehicle_service_calendar/views/calendar_event_views.xml
odoo/addons/fleet_vehicle_service_calendar/views/fleet_vehicle_log_services_views.xml
odoo14_addon_fleet_vehicle_service_calendar-14.0.1.0.1.dev12.dist-info/METADATA
odoo14_addon_fleet_vehicle_service_calendar-14.0.1.0.1.dev12.dist-info/WHEEL
odoo14_addon_fleet_vehicle_service_calendar-14.0.1.0.1.dev12.dist-info/top_level.txt
odoo14_addon_fleet_vehicle_service_calendar-14.0.1.0.1.dev12.dist-info/RECORD
