Metadata-Version: 2.1
Name: odoo14-addon-fleet-vehicle-service-calendar
Version: 14.0.1.0.1.dev12
Summary: Add a smart button in services to schedule meetings.
Home-page: https://github.com/OCA/fleet
Author: Druidoo, Odoo Community Association (OCA)
Author-email: support@odoo-community.org
License: AGPL-3
Platform: UNKNOWN
Classifier: Programming Language :: Python
Classifier: Framework :: Odoo
Classifier: Framework :: Odoo :: 14.0
Classifier: License :: OSI Approved :: GNU Affero General Public License v3
Classifier: Development Status :: 5 - Production/Stable
Requires-Python: >=3.6
Requires-Dist: odoo14-addon-fleet-vehicle-service-kanban
Requires-Dist: odoo <14.1dev,>=14.0a
